[
    {
        "id": "63",
        "name": "Надувные катамараны FISHER",
        "description": "Надувные катамараны FISHER до последнего рестайлинга назывались TRAVEL.",
        "title": "FISHER",
        "sort": "5",
        "icon": "data/1/kateg-menu/fisher 1.png",
        "active": "",
        "models": [
            {
                "id": "80",
                "model": "fisher390",
                "name": "FISHER 390",
                "sort": "1",
                "active": "active"
            },
            {
                "id": "81",
                "model": "fisher460",
                "name": "FISHER 460",
                "sort": "2",
                "active": ""
            },
            {
                "id": "82",
                "model": "fisher530",
                "name": "FISHER 530",
                "sort": "3",
                "active": ""
            },
            {
                "id": "84",
                "model": "fisher590",
                "name": "FISHER 590",
                "sort": "4",
                "active": ""
            },
            {
                "id": "85",
                "model": "fisher591",
                "name": "FISHER 591",
                "sort": "5",
                "active": ""
            },
            {
                "id": "86",
                "model": "fisher660",
                "name": "FISHER 660",
                "sort": "6",
                "active": ""
            },
            {
                "id": "89",
                "model": "fisher730",
                "name": "FISHER 730",
                "sort": "7",
                "active": ""
            },
            {
                "id": "136",
                "model": "fisher731",
                "name": "FISHER 731",
                "sort": "8",
                "active": ""
            },
            {
                "id": "137",
                "model": "fisher790",
                "name": "FISHER 790",
                "sort": "9",
                "active": ""
            }
        ]
    },
    {
        "id": "64",
        "name": "Катамараны пвх SEA FISHER",
        "title": "SEA FISHER",
        "description": "Катамараны ПВХ для морской рыбалки, сплавов и путешествий",
        "sort": "6",
        "icon": "data/1/kateg-menu/seafisher 1.png",
        "active": "",
        "models": [
            {
                "id": "65",
                "model": "seafisher410",
                "name": "SEA FISHER 410",
                "sort": "1",
                "active": "active"
            },
            {
                "id": "66",
                "model": "seafisher480",
                "name": "SEA FISHER 480",
                "sort": "2",
                "active": ""
            },
            {
                "id": "67",
                "model": "seafisher550",
                "name": "SEA FISHER 550",
                "sort": "3",
                "active": ""
            },
            {
                "id": "68",
                "model": "seafisher610",
                "name": "SEA FISHER 610",
                "sort": "4",
                "active": ""
            },
            {
                "id": "139",
                "model": "seafisher611",
                "name": "SEA FISHER 611",
                "sort": "5",
                "active": ""
            },
            {
                "id": "69",
                "model": "seafisher680",
                "name": "SEA FISHER 680",
                "sort": "6",
                "active": ""
            },
            {
                "id": "70",
                "model": "seafisher750",
                "name": "SEA FISHER 750",
                "sort": "7",
                "active": ""
            },
            {
                "id": "144",
                "model": "seafisher751",
                "name": "SEA FISHER 751",
                "sort": "8",
                "active": ""
            },
            {
                "id": "71",
                "model": "seafisher800",
                "name": "SEA FISHER 800",
                "sort": "9",
                "active": ""
            }
        ]
    },
    {
        "id": "73",
        "name": "Катамараны для сплава TRAVEL",
        "title": "TRAVEL",
        "description": "Катамараны TRAVEL — одни из самых больших надувных катамаранов, производимые компанией BOATHOUSE.",
        "sort": "7",
        "icon": "",
        "active": "",
        "models": [
            {
                "id": "212",
                "model": "travel430",
                "name": "TRAVEL 430",
                "sort": "1",
                "active": "active"
            },
            {
                "id": "213",
                "model": "travel500",
                "name": "TRAVEL 500",
                "sort": "1",
                "active": ""
            },
            {
                "id": "214",
                "model": "travel570",
                "name": "TRAVEL 570",
                "sort": "1",
                "active": ""
            },
            {
                "id": "216",
                "model": "travel630",
                "name": "TRAVEL 630",
                "sort": "1",
                "active": ""
            },
            {
                "id": "217",
                "model": "travel631",
                "name": "TRAVEL 631",
                "sort": "1",
                "active": ""
            },
            {
                "id": "218",
                "model": "travel700",
                "name": "TRAVEL 700",
                "sort": "1",
                "active": ""
            },
            {
                "id": "221",
                "model": "travel770",
                "name": "TRAVEL 770",
                "sort": "1",
                "active": ""
            },
            {
                "id": "224",
                "model": "travel771",
                "name": "TRAVEL 771",
                "sort": "1",
                "active": ""
            },
            {
                "id": "225",
                "model": "travel830",
                "name": "TRAVEL 830",
                "sort": "1",
                "active": ""
            }
        ]
    },
    {
        "id": "81",
        "name": "Морские катамараны TRAVEL MAX",
        "title": "TRAVEL MAX",
        "description": "Морские надувные катамараны TRAVEL MAX для путешествий, рыбалки на море, в океане, коммерческого использования",
        "sort": "8",
        "icon": "",
        "active": "",
        "models": [
            {
                "id": "302",
                "model": "travelmax460",
                "name": "TRAVEL MAX 460",
                "sort": "1",
                "active": "active"
            },
            {
                "id": "303",
                "model": "travelmax530",
                "name": "TRAVEL MAX 530",
                "sort": "1",
                "active": ""
            },
            {
                "id": "304",
                "model": "travelmax590",
                "name": "TRAVEL MAX 590",
                "sort": "1",
                "active": ""
            },
            {
                "id": "306",
                "model": "travelmax660",
                "name": "TRAVEL MAX 660",
                "sort": "1",
                "active": ""
            },
            {
                "id": "307",
                "model": "travelmax661",
                "name": "TRAVEL MAX 661",
                "sort": "1",
                "active": ""
            },
            {
                "id": "308",
                "model": "travelmax730",
                "name": "TRAVEL MAX 730",
                "sort": "1",
                "active": ""
            },
            {
                "id": "309",
                "model": "travelmax790",
                "name": "TRAVEL MAX 790",
                "sort": "1",
                "active": ""
            },
            {
                "id": "310",
                "model": "travelmax791",
                "name": "TRAVEL MAX 791",
                "sort": "1",
                "active": ""
            },
            {
                "id": "311",
                "model": "travelmax860",
                "name": "TRAVEL MAX 860",
                "sort": "1",
                "active": ""
            }
        ]
    },
    {
        "id": "60",
        "name": "Транцевые байдарки SPORT",
        "title": "SPORT",
        "description": "Транцевые байдарки SPORT были разработаны для рыбалки, подводной охоты и путешествий, в том числе повышенной сложности.",
        "sort": "3",
        "icon": "",
        "active": "",
        "models": [
            {
                "id": "72",
                "model": "sport310",
                "name": "SPORT 310",
                "sort": "1",
                "active": "active"
            },
            {
                "id": "73",
                "model": "sport370",
                "name": "SPORT 370",
                "sort": "1",
                "active": ""
            },
            {
                "id": "74",
                "model": "sport435",
                "name": "SPORT 435",
                "sort": "1",
                "active": ""
            },
            {
                "id": "75",
                "model": "sport500",
                "name": "SPORT 500",
                "sort": "1",
                "active": ""
            },
            {
                "id": "76",
                "model": "sport560",
                "name": "SPORT 560",
                "sort": "1",
                "active": ""
            }, 
            {
                "id": "77",
                "model": "sport625",
                "name": "SPORT 625",
                "sort": "1",
                "active": ""
            }, 
            {
                "id": "78",
                "model": "sport685",
                "name": "SPORT 685",
                "sort": "1",
                "active": ""
            }, 
            {
                "id": "79",
                "model": "sport686",
                "name": "SPORT 686",
                "sort": "1",
                "active": ""
            }, 
            {
                "id": "146",
                "model": "sport561",
                "name": "SPORT 561",
                "sort": "1",
                "active": ""
            }, 
            {
                "id": "151",
                "model": "sport750",
                "name": "SPORT 750",
                "sort": "1",
                "active": ""
            }
        ]
    },
    {
        "id": "59",
        "name": "Надувные байдарки STREAM",
        "title": "STREAM",
        "description": "Надувные байдарки STREAM по своей конструкции еще можно назвать каркасно-надувными.",
        "sort": "3",
        "icon": "",
        "active": "",
        "models": [
            {
                "id": "50",
                "model": "stream300",
                "name": "STREAM 300",
                "sort": "1",
                "active": "active"
            },
            {
                "id": "51",
                "model": "stream360",
                "name": "STREAM 360",
                "sort": "1",
                "active": ""
            },
            {
                "id": "52",
                "model": "stream425",
                "name": "STREAM 425",
                "sort": "1",
                "active": ""
            },
            {
                "id": "53",
                "model": "stream485",
                "name": "STREAM 485",
                "sort": "1",
                "active": ""
            },
            {
                "id": "54",
                "model": "stream550",
                "name": "STREAM 550",
                "sort": "1",
                "active": ""
            }, 
            {
                "id": "55",
                "model": "stream610",
                "name": "STREAM 610",
                "sort": "1",
                "active": ""
            }, 
            {
                "id": "57",
                "model": "stream675",
                "name": "STREAM 675",
                "sort": "1",
                "active": ""
            }, 
            {
                "id": "132",
                "model": "stream680",
                "name": "STREAM 680",
                "sort": "1",
                "active": ""
            }
        ]
    },
    {
        "id": "81",
        "name": "Коммерческие катамараны TRAVEL XXL",
        "title": "TRAVEL XXL",
        "description": "Катамараны TRAVEL XXL созданы на базе катамаранов TRAVEL MAX. Основное их назначение – использование в коммерческих целях для перевозки людей ..",
        "sort": "3",
        "icon": "",
        "active": "",
        "models": [
            {
                "id": "504",
                "model": "travelxxl590",
                "name": "TRAVEL XXL 590",
                "sort": "1",
                "active": "active"
            },
            {
                "id": "505",
                "model": "travelxxl660",
                "name": "TRAVEL XXL 660",
                "sort": "1",
                "active": ""
            },
            {
                "id": "506",
                "model": "travelxxl730",
                "name": "TRAVEL XXL 730",
                "sort": "1",
                "active": ""
            },
            {
                "id": "507",
                "model": "travelxxl790",
                "name": "TRAVEL XXL 790",
                "sort": "1",
                "active": ""
            },
            {
                "id": "508",
                "model": "travelxxl860",
                "name": "TRAVEL XXL 860",
                "sort": "1",
                "active": ""
            }
        ]
    },
    {
        "id": "75",
        "name": "Мини катамараны SUPKAT, MINIKAT",
        "title": "SUPKAT, MINIKAT",
        "description": "Мини катамараны | SUP надувные катамараны для сплава, рыбалки",
        "sort": "3",
        "icon": "",
        "active": "",
        "models": [
            {
                "id": "283",
                "model": "supkat",
                "name": "SUPKAT",
                "sort": "1",
                "active": "active"
            },
            {
                "id": "565",
                "model": "supkatxl",
                "name": "SUPKAT XL",
                "sort": "1",
                "active": ""
            },
            {
                "id": "566",
                "model": "minikat",
                "name": "MINIKAT",
                "sort": "1",
                "active": ""
            },
            {
                "id": "567",
                "model": "minikatxl",
                "name": "MINIKAT XL",
                "sort": "1",
                "active": ""
            },
            {
                "id": "568",
                "model": "minikatxxl",
                "name": "MINIKAT XXL",
                "sort": "1",
                "active": ""
            }
        ]
    },
    {
        "id": "61",
        "name": "Легкие катамараны SMART FISHER",
        "title": "SMART FISHER",
        "description": "Легкие катамараны SMART FISHER – легкие компактные надувные катамараны, специально предназначенные для рыбалки и охоты ...",
        "sort": "3",
        "icon": "",
        "active": "active",
        "models": [
            {
                "id": "59",
                "model": "smartfisher370",
                "name": "SMART FISHER 370",
                "sort": "1",
                "active": ""
            },
            {
                "id": "60",
                "model": "smartfisher440",
                "name": "SMART FISHER 440",
                "sort": "1",
                "active": ""
            },
            {
                "id": "61",
                "model": "smartfisher500",
                "name": "SMART FISHER 500",
                "sort": "1",
                "active": "active"
            },
            {
                "id": "62",
                "model": "smartfisher570",
                "name": "SMART FISHER 570",
                "sort": "1",
                "active": ""
            },
            {
                "id": "153",
                "model": "smartfisher571",
                "name": "SMART FISHER 571",
                "sort": "1",
                "active": ""
            },
            {
                "id": "154",
                "model": "smartfisher640",
                "name": "SMART FISHER 640",
                "sort": "1",
                "active": ""
            },
            {
                "id": "63",
                "model": "smartfisher700",
                "name": "SMART FISHER 700",
                "sort": "1",
                "active": ""
            },
            {
                "id": "159",
                "model": "smartfisher701",
                "name": "SMART FISHER 701",
                "sort": "1",
                "active": ""
            },
            {
                "id": "160",
                "model": "smartfisher770",
                "name": "SMART FISHER 770",
                "sort": "1",
                "active": ""
            }
        ]
    } 
]